icon_picker_widget/__init__.py
icon_picker_widget/apps.py
icon_picker_widget/widgets.py
icon_picker_widget/static/icon_picker_widget/css/style.css
icon_picker_widget/static/icon_picker_widget/js/npick.js
django_material_icon_widget-0.1.2.dist-info/LICENSE
django_material_icon_widget-0.1.2.dist-info/METADATA
django_material_icon_widget-0.1.2.dist-info/WHEEL
django_material_icon_widget-0.1.2.dist-info/top_level.txt
django_material_icon_widget-0.1.2.dist-info/RECORD
