Metadata-Version: 2.1
Name: django-material-icon-widget
Version: 0.1.2
Summary: Icon Picker for admin panel In Django
Home-page: https://github.com/adieyal/django-material-icon-widget
Author: Adi Eyal
Author-email: adi@openup.org.za
License: MIT
Download-URL: https://github.com/adieyal/django-material-icon-widget/archive/v0.1.2.tar.gz
Keywords: widget,utility
Platform: UNKNOWN
Classifier: Development Status :: 4 - Beta
Classifier: Intended Audience :: Developers
Classifier: Topic :: Software Development :: Build Tools
Classifier: License :: OSI Approved :: MIT License
Classifier: Programming Language :: Python :: 3
Classifier: Programming Language :: Python :: 3.4
Classifier: Programming Language :: Python :: 3.5
Classifier: Programming Language :: Python :: 3.6
Classifier: Topic :: Software Development
Classifier: Topic :: Software Development :: Libraries :: Python Modules
